weldbuild/__init__.py
weldbuild/deps.py
weldbuild/deps/libzip-1.10.1-win32.zip
weldbuild/deps/python-3.11.5-win32.zip
weldbuild/deps/zlib-1.3-win32.zip
weldbuild/platforms/__init__.py
weldbuild/platforms/android.py
weldbuild/platforms/windows.py
weldbuild/platforms/win32/cpp/include/app.h
weldbuild/platforms/win32/cpp/include/appres.h
weldbuild/platforms/win32/cpp/include/precompiled.h
weldbuild/platforms/win32/cpp/src/app.cpp
weldbuild/platforms/win32/cpp/src/appres.rc
weldbuild/platforms/win32/cpp/src/main.cpp
weldbuild/platforms/win32/python/src/__boot__.py
weldbuild/utils/png2ico.py
weldbuild/utils/cmake/__init__.py
weldbuild/utils/gradle/__init__.py
weldbuild-1.0.4.dist-info/LICENSE.txt
weldbuild-1.0.4.dist-info/METADATA
weldbuild-1.0.4.dist-info/WHEEL
weldbuild-1.0.4.dist-info/top_level.txt
weldbuild-1.0.4.dist-info/RECORD
