Metadata-Version: 2.1
Name: weldbuild
Version: 1.0.4
Summary: Lightweight deployment tool for Python
Author-email: Dmitriy Lukovenko <mludima23@gmail.com>
Project-URL: Source, https://github.com/a3st/weldbuild
Classifier: Programming Language :: Python :: 3
Classifier: License :: OSI Approved :: MIT License
Classifier: Operating System :: Android
Classifier: Operating System :: Microsoft :: Windows
Classifier: Operating System :: POSIX :: Linux
Requires-Python: >=3.10
License-File: LICENSE.txt
Requires-Dist: Pillow
